cashd/__init__.py
cashd/app.css
cashd/app.py
cashd/db.py
cashd/plot.py
cashd/prefs.py
cashd/startup.pyw
cashd/assets/EurostileExtendedBlack.ttf
cashd/assets/ICO_LogoIcone.ico
cashd/assets/PNG_LogoFavicon.png
cashd/assets/PNG_LogoIcone.png
cashd/assets/SVG_ConfiguracaoAzul.svg
cashd/assets/SVG_ConfiguracaoBranco.svg
cashd/assets/SVG_ContasAzul.svg
cashd/assets/SVG_ContasBranco.svg
cashd/assets/SVG_DadosBranco.svg
cashd/assets/SVG_TransacaoAzul.svg
cashd/assets/SVG_TransacaoBranco.svg
cashd/assets/gh_banner-cashd.png
cashd/pages/__init__.py
cashd/pages/analise.py
cashd/pages/configs.py
cashd/pages/contas.py
cashd/pages/dialogo.py
cashd/pages/transac.py
cashd-0.3.4.post1.dist-info/licenses/LICENSE
cashd-0.3.4.post1.dist-info/METADATA
cashd-0.3.4.post1.dist-info/WHEEL
cashd-0.3.4.post1.dist-info/entry_points.txt
cashd-0.3.4.post1.dist-info/top_level.txt
cashd-0.3.4.post1.dist-info/RECORD
