Metadata-Version: 2.4
Name: cashd
Version: 0.3.4.post1
Summary: Manage a simple cash flow operations on different accounts locally.
Author-email: "Vitor F. Lins" <vflins@live.com>
License: MIT License
Keywords: cash-flow,financial,fiado,sale-on-credit
Classifier: Topic :: Office/Business :: Financial :: Accounting
Classifier: Intended Audience :: Financial and Insurance Industry
Classifier: Intended Audience :: Customer Service
Classifier: Natural Language :: Portuguese (Brazilian)
Classifier: Programming Language :: Python :: 3
Classifier: Programming Language :: Python :: 3.12
Classifier: Programming Language :: Python :: 3.11
Classifier: Programming Language :: Python :: 3.10
Classifier: Development Status :: 4 - Beta
Classifier: Operating System :: Microsoft :: Windows :: Windows 10
Classifier: Operating System :: Microsoft :: Windows :: Windows 11
Classifier: License :: OSI Approved :: MIT License
Requires-Python: <3.13,>3.9
License-File: LICENSE
Requires-Dist: cashd-core==0.3.4
Requires-Dist: taipy==4.*
Requires-Dist: SQLAlchemy==2.*
Requires-Dist: pywebview>=5.0
Requires-Dist: phonenumbers>=8.13.31
Requires-Dist: pandas>=2.2.0
Requires-Dist: pyshortcuts==1.9.0
Requires-Dist: plotly>=5.22.0
Requires-Dist: PyGObject; sys_platform == "linux"
Provides-Extra: dev
Requires-Dist: pytest-cov>=5.0.0; extra == "dev"
Requires-Dist: black>=24.4.2; extra == "dev"
Requires-Dist: ipykernel; extra == "dev"
Requires-Dist: nbformat; extra == "dev"
Dynamic: license-file
